cloudshell/__init__.py
cloudshell/cli/__init__.py
cloudshell/cli/configurator.py
cloudshell/cli/types.py
cloudshell/cli/command_template/__init__.py
cloudshell/cli/command_template/command_template.py
cloudshell/cli/command_template/command_template_executor.py
cloudshell/cli/factory/__init__.py
cloudshell/cli/factory/session_factory.py
cloudshell/cli/service/__init__.py
cloudshell/cli/service/auth_model.py
cloudshell/cli/service/cli.py
cloudshell/cli/service/cli_exception.py
cloudshell/cli/service/cli_service.py
cloudshell/cli/service/cli_service_impl.py
cloudshell/cli/service/command_mode.py
cloudshell/cli/service/command_mode_helper.py
cloudshell/cli/service/console_model.py
cloudshell/cli/service/node.py
cloudshell/cli/service/session_manager.py
cloudshell/cli/service/session_manager_impl.py
cloudshell/cli/service/session_pool.py
cloudshell/cli/service/session_pool_context_manager.py
cloudshell/cli/service/session_pool_manager.py
cloudshell/cli/session/__init__.py
cloudshell/cli/session/connection_params.py
cloudshell/cli/session/console_ssh.py
cloudshell/cli/session/console_telnet.py
cloudshell/cli/session/expect_session.py
cloudshell/cli/session/scpi_session.py
cloudshell/cli/session/session.py
cloudshell/cli/session/session_exceptions.py
cloudshell/cli/session/ssh_session.py
cloudshell/cli/session/tcp_session.py
cloudshell/cli/session/telnet_session.py
cloudshell/cli/session/tl1_session.py
cloudshell/cli/session/helper/__init__.py
cloudshell/cli/session/helper/normalize_buffer.py
tests/__init__.py
tests/conftest.py
tests/cli/__init__.py
tests/cli/test_cli_service_impl.py
tests/cli/test_command_mode.py
tests/cli/test_command_mode_helper.py
tests/cli/test_configurator.py
tests/cli/test_node.py
tests/cli/test_session_manager.py
tests/cli/test_session_pool_context_manager.py
tests/cli/test_session_pool_manager.py
tests/cli/command_template/__init__.py
tests/cli/command_template/test_command_template.py
tests/cli/session/__init__.py
cloudshell_cli-5.0.2.dist-info/LICENSE
cloudshell_cli-5.0.2.dist-info/METADATA
cloudshell_cli-5.0.2.dist-info/WHEEL
cloudshell_cli-5.0.2.dist-info/top_level.txt
cloudshell_cli-5.0.2.dist-info/RECORD
