Metadata-Version: 2.1
Name: cloudshell-cli
Version: 5.0.2
Summary: QualiSystems CloudShell CLI support package
Home-page: https://www.quali.com/
Author: QualiSystems
Author-email: info@qualisystems.com
Requires-Python: ~=3.7
License-File: LICENSE
Requires-Dist: paramiko ~=2.12
Requires-Dist: scp ~=0.14
Requires-Dist: typing-extensions >=4.0
Requires-Dist: attrs >=21
